cabot_alert_slack/__init__.py
cabot_alert_slack/models.py
cabot_alert_slack/urls.py
cabot_alert_slack/views.py
cabot_alert_slack/migrations/0001_initial.py
cabot_alert_slack/migrations/__init__.py
cabot_alert_slack/tests/__init__.py
cabot_alert_slack/tests/test_slack.py
cabot_alert_slack-0.8.3.dist-info/DESCRIPTION.rst
cabot_alert_slack-0.8.3.dist-info/METADATA
cabot_alert_slack-0.8.3.dist-info/RECORD
cabot_alert_slack-0.8.3.dist-info/WHEEL
cabot_alert_slack-0.8.3.dist-info/metadata.json
cabot_alert_slack-0.8.3.dist-info/top_level.txt
