Metadata-Version: 2.0
Name: cabot-alert-slack
Version: 0.8.3
Summary: A slack alert plugin for Cabot by Arachnys
Home-page: http://lblasc.znode.net
Author: Luka Blaskovic
Author-email: lblasc@znode.net
License: UNKNOWN
Download-URL: https://github.com/lblasc/cabot-alert-slack/tarball/0.6
Platform: UNKNOWN
